frappyflaskdataset/__init__.py
frappyflaskdataset/data_set_api.py
frappyflaskdataset-1.3.3.dist-info/LICENSE
frappyflaskdataset-1.3.3.dist-info/METADATA
frappyflaskdataset-1.3.3.dist-info/WHEEL
frappyflaskdataset-1.3.3.dist-info/top_level.txt
frappyflaskdataset-1.3.3.dist-info/RECORD
