Metadata-Version: 2.1
Name: frappyflaskdataset
Version: 1.3.3
Summary: Flask Endpoints for Data Set Management and Retrieval
Home-page: https://github.com/ilfrich/frappy-flask-datasets
Author: Peter Ilfrich
Author-email: das-peter@gmx.de
License: UNKNOWN
Platform: UNKNOWN
Requires-Dist: flask
Requires-Dist: pbu (>=1.0.0)
